flexiparse/__init__.py
flexiparse/main.py
flexiparse-0.4.0.dist-info/METADATA
flexiparse-0.4.0.dist-info/WHEEL
flexiparse-0.4.0.dist-info/entry_points.txt
flexiparse-0.4.0.dist-info/top_level.txt
flexiparse-0.4.0.dist-info/RECORD
