Metadata-Version: 2.1
Name: flexiparse
Version: 0.4.0
Summary: A dynamic JSON parser for OpenSearch API responses.
Home-page: https://github.com/AndrewGordienko/flexiparse
Author: Andrew Gordienko
Author-email: gordienko.adg@gmail.com
Classifier: Programming Language :: Python :: 3
Classifier: License :: OSI Approved :: MIT License
Classifier: Operating System :: OS Independent
Requires-Python: >=3.6
Requires-Dist: pandas>=1.0.0
